Binance_Data_Getter/Binance_Data_Getter.py
Binance_Data_Getter/Create_Candles.py
Binance_Data_Getter/Temp_Fix_BTC.py
Binance_Data_Getter/Unpack_Zips.py
Binance_Data_Getter/__init__.py
Binance_Data_Getter/download-aggTrade.py
Binance_Data_Getter/download-kline.py
Binance_Data_Getter/download-trade.py
Binance_Data_Getter/enums.py
Binance_Data_Getter/functions_and_stuff.py
Binance_Data_Getter/utility.py
Binance_Data_Getter-0.54.dist-info/LICENSE
Binance_Data_Getter-0.54.dist-info/METADATA
Binance_Data_Getter-0.54.dist-info/WHEEL
Binance_Data_Getter-0.54.dist-info/top_level.txt
Binance_Data_Getter-0.54.dist-info/RECORD
