Metadata-Version: 2.1
Name: Binance_Data_Getter
Version: 0.54
Summary: Used to extract and process data from Binance
Home-page: https://github.com/mario-likes-camels/Binance_Data_Getter
Author: Patrick
Author-email: hi_in@hotmail.com
License: MIT
Platform: UNKNOWN
License-File: LICENSE
